scheme/timezone.py
scheme/common.py
scheme/surrogate.py
scheme/interpolation.py
scheme/exceptions.py
scheme/element.py
scheme/util.py
scheme/format.py
scheme/field.py
scheme/__init__.py
scheme/fields/boolean.py
scheme/fields/__init__.py
scheme/fields/date.py
scheme/fields/email.py
scheme/fields/error.py
scheme/fields/time.py
scheme/fields/datetime.py
scheme/fields/definition.py
scheme/fields/surrogate.py
scheme/fields/sequence.py
scheme/fields/decimal.py
scheme/fields/token.py
scheme/fields/object.py
scheme/fields/uuid.py
scheme/fields/map.py
scheme/fields/float.py
scheme/fields/integer.py
scheme/fields/enumeration.py
scheme/fields/binary.py
scheme/fields/union.py
scheme/fields/text.py
scheme/fields/structure.py
scheme/fields/tuple.py
scheme/formats/urlencoded.py
scheme/formats/json.py
scheme/formats/yaml.py
scheme/formats/structuredtext.py
scheme/formats/xml.py
scheme/formats/__init__.py
scheme/formats/csv.py
scheme/doc/__init__.py
scheme/doc/generator.py
scheme/doc/domain.py
scheme-2.0.2.dist-info/top_level.txt
scheme-2.0.2.dist-info/METADATA
scheme-2.0.2.dist-info/DESCRIPTION.rst
scheme-2.0.2.dist-info/metadata.json
scheme-2.0.2.dist-info/WHEEL
scheme-2.0.2.dist-info/RECORD
